log2fast_fastapi/__init__.py
log2fast_fastapi/__version__.py
log2fast_fastapi/base.py
log2fast_fastapi/formatters.py
log2fast_fastapi/middleware.py
log2fast_fastapi/settings.py
log2fast_fastapi-0.1.0.dist-info/licenses/LICENSE
log2fast_fastapi-0.1.0.dist-info/METADATA
log2fast_fastapi-0.1.0.dist-info/WHEEL
log2fast_fastapi-0.1.0.dist-info/top_level.txt
log2fast_fastapi-0.1.0.dist-info/RECORD
