Metadata-Version: 2.4
Name: log2fast-fastapi
Version: 0.1.0
Summary: Advanced logging module for FastAPI - Designed for Solautyc Team internal use
Author-email: Angel Daniel Sanchez Castillo <angeldaniel.sanchezcastillo@gmail.com>
License: MIT License
Project-URL: Homepage, https://github.com/AngelDanielSanchezCastillo/log2fast-fastapi
Project-URL: Documentation, https://github.com/AngelDanielSanchezCastillo/log2fast-fastapi/tree/main/docs
Project-URL: Repository, https://github.com/AngelDanielSanchezCastillo/log2fast-fastapi
Project-URL: Issues, https://github.com/AngelDanielSanchezCastillo/log2fast-fastapi/issues
Keywords: fastapi,logging,rotation,colored-logs,structured-logging,middleware
Classifier: Development Status :: 3 - Alpha
Classifier: Intended Audience :: Developers
Classifier: License :: OSI Approved :: MIT License
Classifier: Programming Language :: Python :: 3
Classifier: Programming Language :: Python :: 3.10
Classifier: Programming Language :: Python :: 3.11
Classifier: Programming Language :: Python :: 3.12
Classifier: Framework :: FastAPI
Classifier: Topic :: System :: Logging
Classifier: Topic :: Software Development :: Libraries :: Python Modules
Requires-Python: >=3.10
License-File: LICENSE
Requires-Dist: fastapi>=0.100.0
Requires-Dist: pydantic>=2.0.0
Requires-Dist: pydantic-settings>=2.0.0
Provides-Extra: dev
Requires-Dist: pytest>=7.0.0; extra == "dev"
Requires-Dist: pytest-asyncio>=0.21.0; extra == "dev"
Requires-Dist: httpx>=0.24.0; extra == "dev"
Requires-Dist: mypy>=1.0.0; extra == "dev"
Dynamic: license-file
